LICENSE.txt
MANIFEST.in
README.rst
setup.py
yomo/__init__.py
yomo/_version.py
yomo/codes4data.py
yomo/codes4figures.py
yomo.egg-info/PKG-INFO
yomo.egg-info/SOURCES.txt
yomo.egg-info/dependency_links.txt
yomo.egg-info/top_level.txt