Metadata-Version: 1.1
Name: yomo
Version: 0.0.11
Summary: Python 3 modules for atmospheric research, especially airborne sunphotometry.
Home-page: https://pypi.python.org/pypi/yomo/
Author: Yohei Shinozuka
Author-email: Yohei.Shinozuka@nasa.gov
License: MIT
Platform: UNKNOWN
Classifier: License :: OSI Approved :: MIT License
Classifier: Programming Language :: Python :: 3.6
